{
  "GMNCBMLIHPE": [
    {
      "OLDNPNKKDNE": 47001001,
      "MONKHGDIFOI": 47001,
      "DIIDBBGLDOL": "POText_005",
      "OMPENGGFEFF": "POText_109",
      "KEGJJDPAKOH": 1,
      "OEAEJKCIIGP": "",
      "PLHNMNLGMFE": "POText_113",
      "GOJEHMGFBPK": "POText_113",
      "BGFCAHFBJCO": 1,
      "IIEMNPJFNJD": "Assets/NapResources/UI/Sprite/MainCityNyakichi/Packer/StickerFinish.png",
      "OCNMOCIEKFJ": ""
    },
    {
      "OLDNPNKKDNE": 47001002,
      "MONKHGDIFOI": 47001,
      "DIIDBBGLDOL": "POText_006",
      "OMPENGGFEFF": "POText_109",
      "KEGJJDPAKOH": 2,
      "OEAEJKCIIGP": "POText_102",
      "PLHNMNLGMFE": "POText_125",
      "GOJEHMGFBPK": "POText_125",
      "BGFCAHFBJCO": 1,
      "IIEMNPJFNJD": "Assets/NapResources/UI/Sprite/MainCityNyakichi/Packer/StickerFinish.png",
      "OCNMOCIEKFJ": "POText_112"
    },
    {
      "OLDNPNKKDNE": 47001003,
      "MONKHGDIFOI": 47001,
      "DIIDBBGLDOL": "POText_007",
      "OMPENGGFEFF": "POText_109",
      "KEGJJDPAKOH": 2,
      "OEAEJKCIIGP": "POText_102",
      "PLHNMNLGMFE": "POText_126",
      "GOJEHMGFBPK": "POText_126",
      "BGFCAHFBJCO": 1,
      "IIEMNPJFNJD": "Assets/NapResources/UI/Sprite/MainCityNyakichi/Packer/StickerFinish.png",
      "OCNMOCIEKFJ": "POText_112"
    },
    {
      "OLDNPNKKDNE": 47001004,
      "MONKHGDIFOI": 47001,
      "DIIDBBGLDOL": "POText_008",
      "OMPENGGFEFF": "POText_109",
      "KEGJJDPAKOH": 2,
      "OEAEJKCIIGP": "POText_102",
      "PLHNMNLGMFE": "POText_127",
      "GOJEHMGFBPK": "POText_127",
      "BGFCAHFBJCO": 1,
      "IIEMNPJFNJD": "Assets/NapResources/UI/Sprite/MainCityNyakichi/Packer/StickerFinish.png",
      "OCNMOCIEKFJ": "POText_112"
    },
    {
      "OLDNPNKKDNE": 47001005,
      "MONKHGDIFOI": 47001,
      "DIIDBBGLDOL": "POText_009",
      "OMPENGGFEFF": "POText_109",
      "KEGJJDPAKOH": 2,
      "OEAEJKCIIGP": "POText_102",
      "PLHNMNLGMFE": "POText_128",
      "GOJEHMGFBPK": "POText_128",
      "BGFCAHFBJCO": 1,
      "IIEMNPJFNJD": "Assets/NapResources/UI/Sprite/MainCityNyakichi/Packer/StickerFinish.png",
      "OCNMOCIEKFJ": "POText_112"
    },
    {
      "OLDNPNKKDNE": 47001006,
      "MONKHGDIFOI": 47001,
      "DIIDBBGLDOL": "POText_010",
      "OMPENGGFEFF": "POText_109",
      "KEGJJDPAKOH": 2,
      "OEAEJKCIIGP": "POText_102",
      "PLHNMNLGMFE": "POText_129",
      "GOJEHMGFBPK": "POText_129",
      "BGFCAHFBJCO": 1,
      "IIEMNPJFNJD": "Assets/NapResources/UI/Sprite/MainCityNyakichi/Packer/StickerFinish.png",
      "OCNMOCIEKFJ": "POText_112"
    },
    {
      "OLDNPNKKDNE": 47001007,
      "MONKHGDIFOI": 47001,
      "DIIDBBGLDOL": "POText_011",
      "OMPENGGFEFF": "POText_109",
      "KEGJJDPAKOH": 2,
      "OEAEJKCIIGP": "POText_102",
      "PLHNMNLGMFE": "POText_130",
      "GOJEHMGFBPK": "POText_130",
      "BGFCAHFBJCO": 1,
      "IIEMNPJFNJD": "Assets/NapResources/UI/Sprite/MainCityNyakichi/Packer/StickerFinish.png",
      "OCNMOCIEKFJ": "POText_112"
    },
    {
      "OLDNPNKKDNE": 47001008,
      "MONKHGDIFOI": 47001,
      "DIIDBBGLDOL": "POText_012",
      "OMPENGGFEFF": "POText_109",
      "KEGJJDPAKOH": 1,
      "OEAEJKCIIGP": "",
      "PLHNMNLGMFE": "POText_162",
      "GOJEHMGFBPK": "POText_170",
      "BGFCAHFBJCO": 1,
      "IIEMNPJFNJD": "Assets/NapResources/UI/Sprite/MainCityNyakichi/Packer/StickerFinish.png",
      "OCNMOCIEKFJ": ""
    },
    {
      "OLDNPNKKDNE": 47001009,
      "MONKHGDIFOI": 47001,
      "DIIDBBGLDOL": "POText_013",
      "OMPENGGFEFF": "POText_109",
      "KEGJJDPAKOH": 1,
      "OEAEJKCIIGP": "",
      "PLHNMNLGMFE": "POText_163",
      "GOJEHMGFBPK": "POText_171",
      "BGFCAHFBJCO": 1,
      "IIEMNPJFNJD": "Assets/NapResources/UI/Sprite/MainCityNyakichi/Packer/StickerFinish.png",
      "OCNMOCIEKFJ": ""
    },
    {
      "OLDNPNKKDNE": 47001010,
      "MONKHGDIFOI": 47001,
      "DIIDBBGLDOL": "POText_014",
      "OMPENGGFEFF": "POText_109",
      "KEGJJDPAKOH": 1,
      "OEAEJKCIIGP": "",
      "PLHNMNLGMFE": "POText_164",
      "GOJEHMGFBPK": "POText_172",
      "BGFCAHFBJCO": 1,
      "IIEMNPJFNJD": "Assets/NapResources/UI/Sprite/MainCityNyakichi/Packer/StickerFinish.png",
      "OCNMOCIEKFJ": ""
    },
    {
      "OLDNPNKKDNE": 47001011,
      "MONKHGDIFOI": 47001,
      "DIIDBBGLDOL": "POText_015",
      "OMPENGGFEFF": "POText_109",
      "KEGJJDPAKOH": 1,
      "OEAEJKCIIGP": "",
      "PLHNMNLGMFE": "POText_165",
      "GOJEHMGFBPK": "POText_173",
      "BGFCAHFBJCO": 1,
      "IIEMNPJFNJD": "Assets/NapResources/UI/Sprite/MainCityNyakichi/Packer/StickerFinish.png",
      "OCNMOCIEKFJ": ""
    },
    {
      "OLDNPNKKDNE": 47001012,
      "MONKHGDIFOI": 47001,
      "DIIDBBGLDOL": "POText_016",
      "OMPENGGFEFF": "POText_109",
      "KEGJJDPAKOH": 1,
      "OEAEJKCIIGP": "",
      "PLHNMNLGMFE": "POText_169",
      "GOJEHMGFBPK": "POText_177",
      "BGFCAHFBJCO": 1,
      "IIEMNPJFNJD": "Assets/NapResources/UI/Sprite/MainCityNyakichi/Packer/StickerFinish.png",
      "OCNMOCIEKFJ": ""
    },
    {
      "OLDNPNKKDNE": 47001013,
      "MONKHGDIFOI": 47001,
      "DIIDBBGLDOL": "POText_017",
      "OMPENGGFEFF": "POText_109",
      "KEGJJDPAKOH": 1,
      "OEAEJKCIIGP": "",
      "PLHNMNLGMFE": "POText_166",
      "GOJEHMGFBPK": "POText_174",
      "BGFCAHFBJCO": 1,
      "IIEMNPJFNJD": "Assets/NapResources/UI/Sprite/MainCityNyakichi/Packer/StickerFinish.png",
      "OCNMOCIEKFJ": ""
    },
    {
      "OLDNPNKKDNE": 47001014,
      "MONKHGDIFOI": 47001,
      "DIIDBBGLDOL": "POText_018",
      "OMPENGGFEFF": "POText_109",
      "KEGJJDPAKOH": 1,
      "OEAEJKCIIGP": "",
      "PLHNMNLGMFE": "POText_167",
      "GOJEHMGFBPK": "POText_175",
      "BGFCAHFBJCO": 1,
      "IIEMNPJFNJD": "Assets/NapResources/UI/Sprite/MainCityNyakichi/Packer/StickerFinish.png",
      "OCNMOCIEKFJ": ""
    },
    {
      "OLDNPNKKDNE": 47001015,
      "MONKHGDIFOI": 47001,
      "DIIDBBGLDOL": "POText_019",
      "OMPENGGFEFF": "POText_109",
      "KEGJJDPAKOH": 1,
      "OEAEJKCIIGP": "",
      "PLHNMNLGMFE": "POText_168",
      "GOJEHMGFBPK": "POText_176",
      "BGFCAHFBJCO": 1,
      "IIEMNPJFNJD": "Assets/NapResources/UI/Sprite/MainCityNyakichi/Packer/StickerFinish.png",
      "OCNMOCIEKFJ": ""
    },
    {
      "OLDNPNKKDNE": 47001016,
      "MONKHGDIFOI": 47001,
      "DIIDBBGLDOL": "POText_020",
      "OMPENGGFEFF": "POText_109",
      "KEGJJDPAKOH": 1,
      "OEAEJKCIIGP": "",
      "PLHNMNLGMFE": "POText_117",
      "GOJEHMGFBPK": "POText_117",
      "BGFCAHFBJCO": 1,
      "IIEMNPJFNJD": "Assets/NapResources/UI/Sprite/MainCityNyakichi/Packer/StickerFinish.png",
      "OCNMOCIEKFJ": ""
    },
    {
      "OLDNPNKKDNE": 47001017,
      "MONKHGDIFOI": 47002,
      "DIIDBBGLDOL": "POText_021",
      "OMPENGGFEFF": "POText_109",
      "KEGJJDPAKOH": 2,
      "OEAEJKCIIGP": "POText_102",
      "PLHNMNLGMFE": "POText_131",
      "GOJEHMGFBPK": "POText_131",
      "BGFCAHFBJCO": 1,
      "IIEMNPJFNJD": "Assets/NapResources/UI/Sprite/MainCityNyakichi/Packer/StickerFinish.png",
      "OCNMOCIEKFJ": "POText_112"
    },
    {
      "OLDNPNKKDNE": 47001018,
      "MONKHGDIFOI": 47002,
      "DIIDBBGLDOL": "POText_022",
      "OMPENGGFEFF": "POText_109",
      "KEGJJDPAKOH": 2,
      "OEAEJKCIIGP": "POText_102",
      "PLHNMNLGMFE": "POText_132",
      "GOJEHMGFBPK": "POText_132",
      "BGFCAHFBJCO": 1,
      "IIEMNPJFNJD": "Assets/NapResources/UI/Sprite/MainCityNyakichi/Packer/StickerFinish.png",
      "OCNMOCIEKFJ": "POText_112"
    },
    {
      "OLDNPNKKDNE": 47001019,
      "MONKHGDIFOI": 47002,
      "DIIDBBGLDOL": "POText_023",
      "OMPENGGFEFF": "POText_109",
      "KEGJJDPAKOH": 2,
      "OEAEJKCIIGP": "POText_102",
      "PLHNMNLGMFE": "POText_133",
      "GOJEHMGFBPK": "POText_133",
      "BGFCAHFBJCO": 1,
      "IIEMNPJFNJD": "Assets/NapResources/UI/Sprite/MainCityNyakichi/Packer/StickerFinish.png",
      "OCNMOCIEKFJ": "POText_112"
    },
    {
      "OLDNPNKKDNE": 47001020,
      "MONKHGDIFOI": 47002,
      "DIIDBBGLDOL": "POText_024",
      "OMPENGGFEFF": "POText_109",
      "KEGJJDPAKOH": 2,
      "OEAEJKCIIGP": "POText_102",
      "PLHNMNLGMFE": "POText_134",
      "GOJEHMGFBPK": "POText_134",
      "BGFCAHFBJCO": 1,
      "IIEMNPJFNJD": "Assets/NapResources/UI/Sprite/MainCityNyakichi/Packer/StickerFinish.png",
      "OCNMOCIEKFJ": "POText_112"
    },
    {
      "OLDNPNKKDNE": 47001021,
      "MONKHGDIFOI": 47002,
      "DIIDBBGLDOL": "POText_025",
      "OMPENGGFEFF": "POText_109",
      "KEGJJDPAKOH": 2,
      "OEAEJKCIIGP": "POText_102",
      "PLHNMNLGMFE": "POText_135",
      "GOJEHMGFBPK": "POText_135",
      "BGFCAHFBJCO": 1,
      "IIEMNPJFNJD": "Assets/NapResources/UI/Sprite/MainCityNyakichi/Packer/StickerFinish.png",
      "OCNMOCIEKFJ": "POText_112"
    },
    {
      "OLDNPNKKDNE": 47001022,
      "MONKHGDIFOI": 47002,
      "DIIDBBGLDOL": "POText_026",
      "OMPENGGFEFF": "POText_109",
      "KEGJJDPAKOH": 2,
      "OEAEJKCIIGP": "POText_102",
      "PLHNMNLGMFE": "POText_136",
      "GOJEHMGFBPK": "POText_136",
      "BGFCAHFBJCO": 1,
      "IIEMNPJFNJD": "Assets/NapResources/UI/Sprite/MainCityNyakichi/Packer/StickerFinish.png",
      "OCNMOCIEKFJ": "POText_112"
    },
    {
      "OLDNPNKKDNE": 47001023,
      "MONKHGDIFOI": 47002,
      "DIIDBBGLDOL": "POText_027",
      "OMPENGGFEFF": "POText_109",
      "KEGJJDPAKOH": 2,
      "OEAEJKCIIGP": "POText_102",
      "PLHNMNLGMFE": "POText_137",
      "GOJEHMGFBPK": "POText_137",
      "BGFCAHFBJCO": 1,
      "IIEMNPJFNJD": "Assets/NapResources/UI/Sprite/MainCityNyakichi/Packer/StickerFinish.png",
      "OCNMOCIEKFJ": "POText_112"
    },
    {
      "OLDNPNKKDNE": 47001024,
      "MONKHGDIFOI": 47002,
      "DIIDBBGLDOL": "POText_028",
      "OMPENGGFEFF": "POText_109",
      "KEGJJDPAKOH": 2,
      "OEAEJKCIIGP": "POText_102",
      "PLHNMNLGMFE": "POText_138",
      "GOJEHMGFBPK": "POText_138",
      "BGFCAHFBJCO": 1,
      "IIEMNPJFNJD": "Assets/NapResources/UI/Sprite/MainCityNyakichi/Packer/StickerFinish.png",
      "OCNMOCIEKFJ": "POText_112"
    },
    {
      "OLDNPNKKDNE": 47001025,
      "MONKHGDIFOI": 47002,
      "DIIDBBGLDOL": "POText_029",
      "OMPENGGFEFF": "POText_109",
      "KEGJJDPAKOH": 2,
      "OEAEJKCIIGP": "POText_102",
      "PLHNMNLGMFE": "POText_139",
      "GOJEHMGFBPK": "POText_139",
      "BGFCAHFBJCO": 1,
      "IIEMNPJFNJD": "Assets/NapResources/UI/Sprite/MainCityNyakichi/Packer/StickerFinish.png",
      "OCNMOCIEKFJ": "POText_112"
    },
    {
      "OLDNPNKKDNE": 47001026,
      "MONKHGDIFOI": 47002,
      "DIIDBBGLDOL": "POText_030",
      "OMPENGGFEFF": "POText_109",
      "KEGJJDPAKOH": 2,
      "OEAEJKCIIGP": "POText_102",
      "PLHNMNLGMFE": "POText_140",
      "GOJEHMGFBPK": "POText_140",
      "BGFCAHFBJCO": 1,
      "IIEMNPJFNJD": "Assets/NapResources/UI/Sprite/MainCityNyakichi/Packer/StickerFinish.png",
      "OCNMOCIEKFJ": "POText_112"
    },
    {
      "OLDNPNKKDNE": 47001027,
      "MONKHGDIFOI": 47002,
      "DIIDBBGLDOL": "POText_031",
      "OMPENGGFEFF": "POText_109",
      "KEGJJDPAKOH": 1,
      "OEAEJKCIIGP": "",
      "PLHNMNLGMFE": "POText_267",
      "GOJEHMGFBPK": "POText_242",
      "BGFCAHFBJCO": 1,
      "IIEMNPJFNJD": "Assets/NapResources/UI/Sprite/MainCityNyakichi/Packer/StickerFinish.png",
      "OCNMOCIEKFJ": ""
    },
    {
      "OLDNPNKKDNE": 47001028,
      "MONKHGDIFOI": 47002,
      "DIIDBBGLDOL": "POText_032",
      "OMPENGGFEFF": "POText_109",
      "KEGJJDPAKOH": 1,
      "OEAEJKCIIGP": "",
      "PLHNMNLGMFE": "POText_268",
      "GOJEHMGFBPK": "POText_243",
      "BGFCAHFBJCO": 1,
      "IIEMNPJFNJD": "Assets/NapResources/UI/Sprite/MainCityNyakichi/Packer/StickerFinish.png",
      "OCNMOCIEKFJ": ""
    },
    {
      "OLDNPNKKDNE": 47001029,
      "MONKHGDIFOI": 47002,
      "DIIDBBGLDOL": "POText_033",
      "OMPENGGFEFF": "POText_109",
      "KEGJJDPAKOH": 1,
      "OEAEJKCIIGP": "",
      "PLHNMNLGMFE": "POText_269",
      "GOJEHMGFBPK": "POText_244",
      "BGFCAHFBJCO": 1,
      "IIEMNPJFNJD": "Assets/NapResources/UI/Sprite/MainCityNyakichi/Packer/StickerFinish.png",
      "OCNMOCIEKFJ": ""
    },
    {
      "OLDNPNKKDNE": 47001030,
      "MONKHGDIFOI": 47002,
      "DIIDBBGLDOL": "POText_034",
      "OMPENGGFEFF": "POText_109",
      "KEGJJDPAKOH": 1,
      "OEAEJKCIIGP": "",
      "PLHNMNLGMFE": "POText_270",
      "GOJEHMGFBPK": "POText_245",
      "BGFCAHFBJCO": 1,
      "IIEMNPJFNJD": "Assets/NapResources/UI/Sprite/MainCityNyakichi/Packer/StickerFinish.png",
      "OCNMOCIEKFJ": ""
    },
    {
      "OLDNPNKKDNE": 47001031,
      "MONKHGDIFOI": 47002,
      "DIIDBBGLDOL": "POText_035",
      "OMPENGGFEFF": "POText_109",
      "KEGJJDPAKOH": 1,
      "OEAEJKCIIGP": "",
      "PLHNMNLGMFE": "POText_271",
      "GOJEHMGFBPK": "POText_246",
      "BGFCAHFBJCO": 1,
      "IIEMNPJFNJD": "Assets/NapResources/UI/Sprite/MainCityNyakichi/Packer/StickerFinish.png",
      "OCNMOCIEKFJ": ""
    },
    {
      "OLDNPNKKDNE": 47001032,
      "MONKHGDIFOI": 47002,
      "DIIDBBGLDOL": "POText_036",
      "OMPENGGFEFF": "POText_109",
      "KEGJJDPAKOH": 1,
      "OEAEJKCIIGP": "",
      "PLHNMNLGMFE": "POText_118",
      "GOJEHMGFBPK": "POText_118",
      "BGFCAHFBJCO": 1,
      "IIEMNPJFNJD": "Assets/NapResources/UI/Sprite/MainCityNyakichi/Packer/StickerFinish.png",
      "OCNMOCIEKFJ": ""
    },
    {
      "OLDNPNKKDNE": 47001033,
      "MONKHGDIFOI": 47003,
      "DIIDBBGLDOL": "POText_037",
      "OMPENGGFEFF": "POText_109",
      "KEGJJDPAKOH": 1,
      "OEAEJKCIIGP": "",
      "PLHNMNLGMFE": "POText_114",
      "GOJEHMGFBPK": "POText_114",
      "BGFCAHFBJCO": 1,
      "IIEMNPJFNJD": "Assets/NapResources/UI/Sprite/MainCityNyakichi/Packer/StickerFinish.png",
      "OCNMOCIEKFJ": ""
    },
    {
      "OLDNPNKKDNE": 47001034,
      "MONKHGDIFOI": 47003,
      "DIIDBBGLDOL": "POText_038",
      "OMPENGGFEFF": "POText_109",
      "KEGJJDPAKOH": 2,
      "OEAEJKCIIGP": "POText_102",
      "PLHNMNLGMFE": "POText_141",
      "GOJEHMGFBPK": "POText_141",
      "BGFCAHFBJCO": 1,
      "IIEMNPJFNJD": "Assets/NapResources/UI/Sprite/MainCityNyakichi/Packer/StickerFinish.png",
      "OCNMOCIEKFJ": "POText_112"
    },
    {
      "OLDNPNKKDNE": 47001035,
      "MONKHGDIFOI": 47003,
      "DIIDBBGLDOL": "POText_039",
      "OMPENGGFEFF": "POText_109",
      "KEGJJDPAKOH": 2,
      "OEAEJKCIIGP": "POText_102",
      "PLHNMNLGMFE": "POText_142",
      "GOJEHMGFBPK": "POText_142",
      "BGFCAHFBJCO": 1,
      "IIEMNPJFNJD": "Assets/NapResources/UI/Sprite/MainCityNyakichi/Packer/StickerFinish.png",
      "OCNMOCIEKFJ": "POText_112"
    },
    {
      "OLDNPNKKDNE": 47001036,
      "MONKHGDIFOI": 47003,
      "DIIDBBGLDOL": "POText_040",
      "OMPENGGFEFF": "POText_109",
      "KEGJJDPAKOH": 2,
      "OEAEJKCIIGP": "POText_102",
      "PLHNMNLGMFE": "POText_143",
      "GOJEHMGFBPK": "POText_143",
      "BGFCAHFBJCO": 1,
      "IIEMNPJFNJD": "Assets/NapResources/UI/Sprite/MainCityNyakichi/Packer/StickerFinish.png",
      "OCNMOCIEKFJ": "POText_112"
    },
    {
      "OLDNPNKKDNE": 47001037,
      "MONKHGDIFOI": 47003,
      "DIIDBBGLDOL": "POText_041",
      "OMPENGGFEFF": "POText_109",
      "KEGJJDPAKOH": 2,
      "OEAEJKCIIGP": "POText_102",
      "PLHNMNLGMFE": "POText_144",
      "GOJEHMGFBPK": "POText_144",
      "BGFCAHFBJCO": 1,
      "IIEMNPJFNJD": "Assets/NapResources/UI/Sprite/MainCityNyakichi/Packer/StickerFinish.png",
      "OCNMOCIEKFJ": "POText_112"
    },
    {
      "OLDNPNKKDNE": 47001038,
      "MONKHGDIFOI": 47003,
      "DIIDBBGLDOL": "POText_042",
      "OMPENGGFEFF": "POText_109",
      "KEGJJDPAKOH": 2,
      "OEAEJKCIIGP": "POText_102",
      "PLHNMNLGMFE": "POText_145",
      "GOJEHMGFBPK": "POText_145",
      "BGFCAHFBJCO": 1,
      "IIEMNPJFNJD": "Assets/NapResources/UI/Sprite/MainCityNyakichi/Packer/StickerFinish.png",
      "OCNMOCIEKFJ": "POText_112"
    },
    {
      "OLDNPNKKDNE": 47001039,
      "MONKHGDIFOI": 47003,
      "DIIDBBGLDOL": "POText_043",
      "OMPENGGFEFF": "POText_109",
      "KEGJJDPAKOH": 1,
      "OEAEJKCIIGP": "",
      "PLHNMNLGMFE": "POText_180",
      "GOJEHMGFBPK": "POText_188",
      "BGFCAHFBJCO": 1,
      "IIEMNPJFNJD": "Assets/NapResources/UI/Sprite/MainCityNyakichi/Packer/StickerFinish.png",
      "OCNMOCIEKFJ": ""
    },
    {
      "OLDNPNKKDNE": 47001040,
      "MONKHGDIFOI": 47003,
      "DIIDBBGLDOL": "POText_044",
      "OMPENGGFEFF": "POText_109",
      "KEGJJDPAKOH": 1,
      "OEAEJKCIIGP": "",
      "PLHNMNLGMFE": "POText_181",
      "GOJEHMGFBPK": "POText_189",
      "BGFCAHFBJCO": 1,
      "IIEMNPJFNJD": "Assets/NapResources/UI/Sprite/MainCityNyakichi/Packer/StickerFinish.png",
      "OCNMOCIEKFJ": ""
    },
    {
      "OLDNPNKKDNE": 47001041,
      "MONKHGDIFOI": 47003,
      "DIIDBBGLDOL": "POText_045",
      "OMPENGGFEFF": "POText_109",
      "KEGJJDPAKOH": 1,
      "OEAEJKCIIGP": "",
      "PLHNMNLGMFE": "POText_182",
      "GOJEHMGFBPK": "POText_190",
      "BGFCAHFBJCO": 1,
      "IIEMNPJFNJD": "Assets/NapResources/UI/Sprite/MainCityNyakichi/Packer/StickerFinish.png",
      "OCNMOCIEKFJ": ""
    },
    {
      "OLDNPNKKDNE": 47001042,
      "MONKHGDIFOI": 47003,
      "DIIDBBGLDOL": "POText_046",
      "OMPENGGFEFF": "POText_109",
      "KEGJJDPAKOH": 1,
      "OEAEJKCIIGP": "",
      "PLHNMNLGMFE": "POText_183",
      "GOJEHMGFBPK": "POText_191",
      "BGFCAHFBJCO": 1,
      "IIEMNPJFNJD": "Assets/NapResources/UI/Sprite/MainCityNyakichi/Packer/StickerFinish.png",
      "OCNMOCIEKFJ": ""
    },
    {
      "OLDNPNKKDNE": 47001043,
      "MONKHGDIFOI": 47003,
      "DIIDBBGLDOL": "POText_047",
      "OMPENGGFEFF": "POText_109",
      "KEGJJDPAKOH": 1,
      "OEAEJKCIIGP": "",
      "PLHNMNLGMFE": "POText_184",
      "GOJEHMGFBPK": "POText_192",
      "BGFCAHFBJCO": 1,
      "IIEMNPJFNJD": "Assets/NapResources/UI/Sprite/MainCityNyakichi/Packer/StickerFinish.png",
      "OCNMOCIEKFJ": ""
    },
    {
      "OLDNPNKKDNE": 47001044,
      "MONKHGDIFOI": 47003,
      "DIIDBBGLDOL": "POText_048",
      "OMPENGGFEFF": "POText_109",
      "KEGJJDPAKOH": 1,
      "OEAEJKCIIGP": "",
      "PLHNMNLGMFE": "POText_185",
      "GOJEHMGFBPK": "POText_193",
      "BGFCAHFBJCO": 1,
      "IIEMNPJFNJD": "Assets/NapResources/UI/Sprite/MainCityNyakichi/Packer/StickerFinish.png",
      "OCNMOCIEKFJ": ""
    },
    {
      "OLDNPNKKDNE": 47001045,
      "MONKHGDIFOI": 47003,
      "DIIDBBGLDOL": "POText_049",
      "OMPENGGFEFF": "POText_109",
      "KEGJJDPAKOH": 1,
      "OEAEJKCIIGP": "",
      "PLHNMNLGMFE": "POText_186",
      "GOJEHMGFBPK": "POText_194",
      "BGFCAHFBJCO": 1,
      "IIEMNPJFNJD": "Assets/NapResources/UI/Sprite/MainCityNyakichi/Packer/StickerFinish.png",
      "OCNMOCIEKFJ": ""
    },
    {
      "OLDNPNKKDNE": 47001046,
      "MONKHGDIFOI": 47003,
      "DIIDBBGLDOL": "POText_050",
      "OMPENGGFEFF": "POText_109",
      "KEGJJDPAKOH": 1,
      "OEAEJKCIIGP": "",
      "PLHNMNLGMFE": "POText_187",
      "GOJEHMGFBPK": "POText_195",
      "BGFCAHFBJCO": 1,
      "IIEMNPJFNJD": "Assets/NapResources/UI/Sprite/MainCityNyakichi/Packer/StickerFinish.png",
      "OCNMOCIEKFJ": ""
    },
    {
      "OLDNPNKKDNE": 47001047,
      "MONKHGDIFOI": 47003,
      "DIIDBBGLDOL": "POText_051",
      "OMPENGGFEFF": "POText_109",
      "KEGJJDPAKOH": 1,
      "OEAEJKCIIGP": "",
      "PLHNMNLGMFE": "POText_119",
      "GOJEHMGFBPK": "POText_119",
      "BGFCAHFBJCO": 1,
      "IIEMNPJFNJD": "Assets/NapResources/UI/Sprite/MainCityNyakichi/Packer/StickerFinish.png",
      "OCNMOCIEKFJ": ""
    },
    {
      "OLDNPNKKDNE": 47001048,
      "MONKHGDIFOI": 47003,
      "DIIDBBGLDOL": "POText_052",
      "OMPENGGFEFF": "POText_109",
      "KEGJJDPAKOH": 1,
      "OEAEJKCIIGP": "",
      "PLHNMNLGMFE": "POText_120",
      "GOJEHMGFBPK": "POText_120",
      "BGFCAHFBJCO": 1,
      "IIEMNPJFNJD": "Assets/NapResources/UI/Sprite/MainCityNyakichi/Packer/StickerFinish.png",
      "OCNMOCIEKFJ": ""
    },
    {
      "OLDNPNKKDNE": 47001049,
      "MONKHGDIFOI": 47004,
      "DIIDBBGLDOL": "POText_053",
      "OMPENGGFEFF": "POText_109",
      "KEGJJDPAKOH": 1,
      "OEAEJKCIIGP": "",
      "PLHNMNLGMFE": "POText_115",
      "GOJEHMGFBPK": "POText_115",
      "BGFCAHFBJCO": 1,
      "IIEMNPJFNJD": "Assets/NapResources/UI/Sprite/MainCityNyakichi/Packer/StickerFinish.png",
      "OCNMOCIEKFJ": ""
    },
    {
      "OLDNPNKKDNE": 47001050,
      "MONKHGDIFOI": 47004,
      "DIIDBBGLDOL": "POText_054",
      "OMPENGGFEFF": "POText_109",
      "KEGJJDPAKOH": 2,
      "OEAEJKCIIGP": "POText_102",
      "PLHNMNLGMFE": "POText_146",
      "GOJEHMGFBPK": "POText_146",
      "BGFCAHFBJCO": 1,
      "IIEMNPJFNJD": "Assets/NapResources/UI/Sprite/MainCityNyakichi/Packer/StickerFinish.png",
      "OCNMOCIEKFJ": "POText_112"
    },
    {
      "OLDNPNKKDNE": 47001051,
      "MONKHGDIFOI": 47004,
      "DIIDBBGLDOL": "POText_055",
      "OMPENGGFEFF": "POText_109",
      "KEGJJDPAKOH": 2,
      "OEAEJKCIIGP": "POText_102",
      "PLHNMNLGMFE": "POText_147",
      "GOJEHMGFBPK": "POText_147",
      "BGFCAHFBJCO": 1,
      "IIEMNPJFNJD": "Assets/NapResources/UI/Sprite/MainCityNyakichi/Packer/StickerFinish.png",
      "OCNMOCIEKFJ": "POText_112"
    },
    {
      "OLDNPNKKDNE": 47001052,
      "MONKHGDIFOI": 47004,
      "DIIDBBGLDOL": "POText_056",
      "OMPENGGFEFF": "POText_109",
      "KEGJJDPAKOH": 2,
      "OEAEJKCIIGP": "POText_102",
      "PLHNMNLGMFE": "POText_148",
      "GOJEHMGFBPK": "POText_148",
      "BGFCAHFBJCO": 1,
      "IIEMNPJFNJD": "Assets/NapResources/UI/Sprite/MainCityNyakichi/Packer/StickerFinish.png",
      "OCNMOCIEKFJ": "POText_112"
    },
    {
      "OLDNPNKKDNE": 47001053,
      "MONKHGDIFOI": 47004,
      "DIIDBBGLDOL": "POText_057",
      "OMPENGGFEFF": "POText_109",
      "KEGJJDPAKOH": 2,
      "OEAEJKCIIGP": "POText_102",
      "PLHNMNLGMFE": "POText_149",
      "GOJEHMGFBPK": "POText_149",
      "BGFCAHFBJCO": 1,
      "IIEMNPJFNJD": "Assets/NapResources/UI/Sprite/MainCityNyakichi/Packer/StickerFinish.png",
      "OCNMOCIEKFJ": "POText_112"
    },
    {
      "OLDNPNKKDNE": 47001054,
      "MONKHGDIFOI": 47004,
      "DIIDBBGLDOL": "POText_058",
      "OMPENGGFEFF": "POText_109",
      "KEGJJDPAKOH": 2,
      "OEAEJKCIIGP": "POText_102",
      "PLHNMNLGMFE": "POText_150",
      "GOJEHMGFBPK": "POText_150",
      "BGFCAHFBJCO": 1,
      "IIEMNPJFNJD": "Assets/NapResources/UI/Sprite/MainCityNyakichi/Packer/StickerFinish.png",
      "OCNMOCIEKFJ": "POText_112"
    },
    {
      "OLDNPNKKDNE": 47001055,
      "MONKHGDIFOI": 47004,
      "DIIDBBGLDOL": "POText_059",
      "OMPENGGFEFF": "POText_109",
      "KEGJJDPAKOH": 2,
      "OEAEJKCIIGP": "POText_102",
      "PLHNMNLGMFE": "POText_151",
      "GOJEHMGFBPK": "POText_151",
      "BGFCAHFBJCO": 1,
      "IIEMNPJFNJD": "Assets/NapResources/UI/Sprite/MainCityNyakichi/Packer/StickerFinish.png",
      "OCNMOCIEKFJ": "POText_112"
    },
    {
      "OLDNPNKKDNE": 47001056,
      "MONKHGDIFOI": 47004,
      "DIIDBBGLDOL": "POText_060",
      "OMPENGGFEFF": "POText_109",
      "KEGJJDPAKOH": 1,
      "OEAEJKCIIGP": "",
      "PLHNMNLGMFE": "POText_212",
      "GOJEHMGFBPK": "POText_220",
      "BGFCAHFBJCO": 1,
      "IIEMNPJFNJD": "Assets/NapResources/UI/Sprite/MainCityNyakichi/Packer/StickerFinish.png",
      "OCNMOCIEKFJ": ""
    },
    {
      "OLDNPNKKDNE": 47001057,
      "MONKHGDIFOI": 47004,
      "DIIDBBGLDOL": "POText_061",
      "OMPENGGFEFF": "POText_109",
      "KEGJJDPAKOH": 1,
      "OEAEJKCIIGP": "",
      "PLHNMNLGMFE": "POText_213",
      "GOJEHMGFBPK": "POText_221",
      "BGFCAHFBJCO": 1,
      "IIEMNPJFNJD": "Assets/NapResources/UI/Sprite/MainCityNyakichi/Packer/StickerFinish.png",
      "OCNMOCIEKFJ": ""
    },
    {
      "OLDNPNKKDNE": 47001058,
      "MONKHGDIFOI": 47004,
      "DIIDBBGLDOL": "POText_062",
      "OMPENGGFEFF": "POText_109",
      "KEGJJDPAKOH": 1,
      "OEAEJKCIIGP": "",
      "PLHNMNLGMFE": "POText_214",
      "GOJEHMGFBPK": "POText_222",
      "BGFCAHFBJCO": 1,
      "IIEMNPJFNJD": "Assets/NapResources/UI/Sprite/MainCityNyakichi/Packer/StickerFinish.png",
      "OCNMOCIEKFJ": ""
    },
    {
      "OLDNPNKKDNE": 47001059,
      "MONKHGDIFOI": 47004,
      "DIIDBBGLDOL": "POText_063",
      "OMPENGGFEFF": "POText_109",
      "KEGJJDPAKOH": 1,
      "OEAEJKCIIGP": "",
      "PLHNMNLGMFE": "POText_215",
      "GOJEHMGFBPK": "POText_223",
      "BGFCAHFBJCO": 1,
      "IIEMNPJFNJD": "Assets/NapResources/UI/Sprite/MainCityNyakichi/Packer/StickerFinish.png",
      "OCNMOCIEKFJ": ""
    },
    {
      "OLDNPNKKDNE": 47001060,
      "MONKHGDIFOI": 47004,
      "DIIDBBGLDOL": "POText_064",
      "OMPENGGFEFF": "POText_109",
      "KEGJJDPAKOH": 1,
      "OEAEJKCIIGP": "",
      "PLHNMNLGMFE": "POText_216",
      "GOJEHMGFBPK": "POText_224",
      "BGFCAHFBJCO": 1,
      "IIEMNPJFNJD": "Assets/NapResources/UI/Sprite/MainCityNyakichi/Packer/StickerFinish.png",
      "OCNMOCIEKFJ": ""
    },
    {
      "OLDNPNKKDNE": 47001061,
      "MONKHGDIFOI": 47004,
      "DIIDBBGLDOL": "POText_065",
      "OMPENGGFEFF": "POText_109",
      "KEGJJDPAKOH": 1,
      "OEAEJKCIIGP": "",
      "PLHNMNLGMFE": "POText_217",
      "GOJEHMGFBPK": "POText_225",
      "BGFCAHFBJCO": 1,
      "IIEMNPJFNJD": "Assets/NapResources/UI/Sprite/MainCityNyakichi/Packer/StickerFinish.png",
      "OCNMOCIEKFJ": ""
    },
    {
      "OLDNPNKKDNE": 47001062,
      "MONKHGDIFOI": 47004,
      "DIIDBBGLDOL": "POText_066",
      "OMPENGGFEFF": "POText_109",
      "KEGJJDPAKOH": 1,
      "OEAEJKCIIGP": "",
      "PLHNMNLGMFE": "POText_218",
      "GOJEHMGFBPK": "POText_226",
      "BGFCAHFBJCO": 1,
      "IIEMNPJFNJD": "Assets/NapResources/UI/Sprite/MainCityNyakichi/Packer/StickerFinish.png",
      "OCNMOCIEKFJ": ""
    },
    {
      "OLDNPNKKDNE": 47001063,
      "MONKHGDIFOI": 47004,
      "DIIDBBGLDOL": "POText_067",
      "OMPENGGFEFF": "POText_109",
      "KEGJJDPAKOH": 1,
      "OEAEJKCIIGP": "",
      "PLHNMNLGMFE": "POText_219",
      "GOJEHMGFBPK": "POText_227",
      "BGFCAHFBJCO": 1,
      "IIEMNPJFNJD": "Assets/NapResources/UI/Sprite/MainCityNyakichi/Packer/StickerFinish.png",
      "OCNMOCIEKFJ": ""
    },
    {
      "OLDNPNKKDNE": 47001064,
      "MONKHGDIFOI": 47004,
      "DIIDBBGLDOL": "POText_068",
      "OMPENGGFEFF": "POText_109",
      "KEGJJDPAKOH": 1,
      "OEAEJKCIIGP": "",
      "PLHNMNLGMFE": "POText_121",
      "GOJEHMGFBPK": "POText_121",
      "BGFCAHFBJCO": 1,
      "IIEMNPJFNJD": "Assets/NapResources/UI/Sprite/MainCityNyakichi/Packer/StickerFinish.png",
      "OCNMOCIEKFJ": ""
    },
    {
      "OLDNPNKKDNE": 47001065,
      "MONKHGDIFOI": 47005,
      "DIIDBBGLDOL": "POText_069",
      "OMPENGGFEFF": "POText_109",
      "KEGJJDPAKOH": 2,
      "OEAEJKCIIGP": "POText_102",
      "PLHNMNLGMFE": "POText_152",
      "GOJEHMGFBPK": "POText_152",
      "BGFCAHFBJCO": 1,
      "IIEMNPJFNJD": "Assets/NapResources/UI/Sprite/MainCityNyakichi/Packer/StickerFinish.png",
      "OCNMOCIEKFJ": "POText_112"
    },
    {
      "OLDNPNKKDNE": 47001066,
      "MONKHGDIFOI": 47005,
      "DIIDBBGLDOL": "POText_070",
      "OMPENGGFEFF": "POText_109",
      "KEGJJDPAKOH": 2,
      "OEAEJKCIIGP": "POText_102",
      "PLHNMNLGMFE": "POText_153",
      "GOJEHMGFBPK": "POText_153",
      "BGFCAHFBJCO": 1,
      "IIEMNPJFNJD": "Assets/NapResources/UI/Sprite/MainCityNyakichi/Packer/StickerFinish.png",
      "OCNMOCIEKFJ": "POText_112"
    },
    {
      "OLDNPNKKDNE": 47001067,
      "MONKHGDIFOI": 47005,
      "DIIDBBGLDOL": "POText_071",
      "OMPENGGFEFF": "POText_109",
      "KEGJJDPAKOH": 2,
      "OEAEJKCIIGP": "POText_102",
      "PLHNMNLGMFE": "POText_154",
      "GOJEHMGFBPK": "POText_154",
      "BGFCAHFBJCO": 1,
      "IIEMNPJFNJD": "Assets/NapResources/UI/Sprite/MainCityNyakichi/Packer/StickerFinish.png",
      "OCNMOCIEKFJ": "POText_112"
    },
    {
      "OLDNPNKKDNE": 47001068,
      "MONKHGDIFOI": 47005,
      "DIIDBBGLDOL": "POText_072",
      "OMPENGGFEFF": "POText_109",
      "KEGJJDPAKOH": 2,
      "OEAEJKCIIGP": "POText_102",
      "PLHNMNLGMFE": "POText_155",
      "GOJEHMGFBPK": "POText_155",
      "BGFCAHFBJCO": 1,
      "IIEMNPJFNJD": "Assets/NapResources/UI/Sprite/MainCityNyakichi/Packer/StickerFinish.png",
      "OCNMOCIEKFJ": "POText_112"
    },
    {
      "OLDNPNKKDNE": 47001069,
      "MONKHGDIFOI": 47005,
      "DIIDBBGLDOL": "POText_073",
      "OMPENGGFEFF": "POText_109",
      "KEGJJDPAKOH": 2,
      "OEAEJKCIIGP": "POText_102",
      "PLHNMNLGMFE": "POText_156",
      "GOJEHMGFBPK": "POText_156",
      "BGFCAHFBJCO": 1,
      "IIEMNPJFNJD": "Assets/NapResources/UI/Sprite/MainCityNyakichi/Packer/StickerFinish.png",
      "OCNMOCIEKFJ": "POText_112"
    },
    {
      "OLDNPNKKDNE": 47001070,
      "MONKHGDIFOI": 47005,
      "DIIDBBGLDOL": "POText_074",
      "OMPENGGFEFF": "POText_109",
      "KEGJJDPAKOH": 1,
      "OEAEJKCIIGP": "",
      "PLHNMNLGMFE": "POText_257",
      "GOJEHMGFBPK": "POText_247",
      "BGFCAHFBJCO": 1,
      "IIEMNPJFNJD": "Assets/NapResources/UI/Sprite/MainCityNyakichi/Packer/StickerFinish.png",
      "OCNMOCIEKFJ": ""
    },
    {
      "OLDNPNKKDNE": 47001071,
      "MONKHGDIFOI": 47005,
      "DIIDBBGLDOL": "POText_075",
      "OMPENGGFEFF": "POText_109",
      "KEGJJDPAKOH": 1,
      "OEAEJKCIIGP": "",
      "PLHNMNLGMFE": "POText_258",
      "GOJEHMGFBPK": "POText_248",
      "BGFCAHFBJCO": 1,
      "IIEMNPJFNJD": "Assets/NapResources/UI/Sprite/MainCityNyakichi/Packer/StickerFinish.png",
      "OCNMOCIEKFJ": ""
    },
    {
      "OLDNPNKKDNE": 47001072,
      "MONKHGDIFOI": 47005,
      "DIIDBBGLDOL": "POText_076",
      "OMPENGGFEFF": "POText_109",
      "KEGJJDPAKOH": 1,
      "OEAEJKCIIGP": "",
      "PLHNMNLGMFE": "POText_259",
      "GOJEHMGFBPK": "POText_249",
      "BGFCAHFBJCO": 1,
      "IIEMNPJFNJD": "Assets/NapResources/UI/Sprite/MainCityNyakichi/Packer/StickerFinish.png",
      "OCNMOCIEKFJ": ""
    },
    {
      "OLDNPNKKDNE": 47001073,
      "MONKHGDIFOI": 47005,
      "DIIDBBGLDOL": "POText_077",
      "OMPENGGFEFF": "POText_109",
      "KEGJJDPAKOH": 1,
      "OEAEJKCIIGP": "",
      "PLHNMNLGMFE": "POText_260",
      "GOJEHMGFBPK": "POText_250",
      "BGFCAHFBJCO": 1,
      "IIEMNPJFNJD": "Assets/NapResources/UI/Sprite/MainCityNyakichi/Packer/StickerFinish.png",
      "OCNMOCIEKFJ": ""
    },
    {
      "OLDNPNKKDNE": 47001074,
      "MONKHGDIFOI": 47005,
      "DIIDBBGLDOL": "POText_078",
      "OMPENGGFEFF": "POText_109",
      "KEGJJDPAKOH": 1,
      "OEAEJKCIIGP": "",
      "PLHNMNLGMFE": "POText_261",
      "GOJEHMGFBPK": "POText_251",
      "BGFCAHFBJCO": 1,
      "IIEMNPJFNJD": "Assets/NapResources/UI/Sprite/MainCityNyakichi/Packer/StickerFinish.png",
      "OCNMOCIEKFJ": ""
    },
    {
      "OLDNPNKKDNE": 47001075,
      "MONKHGDIFOI": 47005,
      "DIIDBBGLDOL": "POText_079",
      "OMPENGGFEFF": "POText_109",
      "KEGJJDPAKOH": 1,
      "OEAEJKCIIGP": "",
      "PLHNMNLGMFE": "POText_262",
      "GOJEHMGFBPK": "POText_252",
      "BGFCAHFBJCO": 1,
      "IIEMNPJFNJD": "Assets/NapResources/UI/Sprite/MainCityNyakichi/Packer/StickerFinish.png",
      "OCNMOCIEKFJ": ""
    },
    {
      "OLDNPNKKDNE": 47001076,
      "MONKHGDIFOI": 47005,
      "DIIDBBGLDOL": "POText_080",
      "OMPENGGFEFF": "POText_109",
      "KEGJJDPAKOH": 1,
      "OEAEJKCIIGP": "",
      "PLHNMNLGMFE": "POText_263",
      "GOJEHMGFBPK": "POText_253",
      "BGFCAHFBJCO": 1,
      "IIEMNPJFNJD": "Assets/NapResources/UI/Sprite/MainCityNyakichi/Packer/StickerFinish.png",
      "OCNMOCIEKFJ": ""
    },
    {
      "OLDNPNKKDNE": 47001077,
      "MONKHGDIFOI": 47005,
      "DIIDBBGLDOL": "POText_081",
      "OMPENGGFEFF": "POText_109",
      "KEGJJDPAKOH": 1,
      "OEAEJKCIIGP": "",
      "PLHNMNLGMFE": "POText_264",
      "GOJEHMGFBPK": "POText_254",
      "BGFCAHFBJCO": 1,
      "IIEMNPJFNJD": "Assets/NapResources/UI/Sprite/MainCityNyakichi/Packer/StickerFinish.png",
      "OCNMOCIEKFJ": ""
    },
    {
      "OLDNPNKKDNE": 47001078,
      "MONKHGDIFOI": 47005,
      "DIIDBBGLDOL": "POText_082",
      "OMPENGGFEFF": "POText_109",
      "KEGJJDPAKOH": 1,
      "OEAEJKCIIGP": "",
      "PLHNMNLGMFE": "POText_265",
      "GOJEHMGFBPK": "POText_255",
      "BGFCAHFBJCO": 1,
      "IIEMNPJFNJD": "Assets/NapResources/UI/Sprite/MainCityNyakichi/Packer/StickerFinish.png",
      "OCNMOCIEKFJ": ""
    },
    {
      "OLDNPNKKDNE": 47001079,
      "MONKHGDIFOI": 47005,
      "DIIDBBGLDOL": "POText_083",
      "OMPENGGFEFF": "POText_109",
      "KEGJJDPAKOH": 1,
      "OEAEJKCIIGP": "",
      "PLHNMNLGMFE": "POText_266",
      "GOJEHMGFBPK": "POText_256",
      "BGFCAHFBJCO": 1,
      "IIEMNPJFNJD": "Assets/NapResources/UI/Sprite/MainCityNyakichi/Packer/StickerFinish.png",
      "OCNMOCIEKFJ": ""
    },
    {
      "OLDNPNKKDNE": 47001080,
      "MONKHGDIFOI": 47005,
      "DIIDBBGLDOL": "POText_084",
      "OMPENGGFEFF": "POText_109",
      "KEGJJDPAKOH": 1,
      "OEAEJKCIIGP": "",
      "PLHNMNLGMFE": "POText_122",
      "GOJEHMGFBPK": "POText_122",
      "BGFCAHFBJCO": 1,
      "IIEMNPJFNJD": "Assets/NapResources/UI/Sprite/MainCityNyakichi/Packer/StickerFinish.png",
      "OCNMOCIEKFJ": ""
    },
    {
      "OLDNPNKKDNE": 47001081,
      "MONKHGDIFOI": 47006,
      "DIIDBBGLDOL": "POText_085",
      "OMPENGGFEFF": "POText_109",
      "KEGJJDPAKOH": 1,
      "OEAEJKCIIGP": "",
      "PLHNMNLGMFE": "POText_116",
      "GOJEHMGFBPK": "POText_116",
      "BGFCAHFBJCO": 1,
      "IIEMNPJFNJD": "Assets/NapResources/UI/Sprite/MainCityNyakichi/Packer/StickerFinish.png",
      "OCNMOCIEKFJ": ""
    },
    {
      "OLDNPNKKDNE": 47001082,
      "MONKHGDIFOI": 47006,
      "DIIDBBGLDOL": "POText_086",
      "OMPENGGFEFF": "POText_109",
      "KEGJJDPAKOH": 2,
      "OEAEJKCIIGP": "POText_102",
      "PLHNMNLGMFE": "POText_157",
      "GOJEHMGFBPK": "POText_157",
      "BGFCAHFBJCO": 1,
      "IIEMNPJFNJD": "Assets/NapResources/UI/Sprite/MainCityNyakichi/Packer/StickerFinish.png",
      "OCNMOCIEKFJ": "POText_112"
    },
    {
      "OLDNPNKKDNE": 47001083,
      "MONKHGDIFOI": 47006,
      "DIIDBBGLDOL": "POText_087",
      "OMPENGGFEFF": "POText_109",
      "KEGJJDPAKOH": 2,
      "OEAEJKCIIGP": "POText_102",
      "PLHNMNLGMFE": "POText_158",
      "GOJEHMGFBPK": "POText_158",
      "BGFCAHFBJCO": 1,
      "IIEMNPJFNJD": "Assets/NapResources/UI/Sprite/MainCityNyakichi/Packer/StickerFinish.png",
      "OCNMOCIEKFJ": "POText_112"
    },
    {
      "OLDNPNKKDNE": 47001084,
      "MONKHGDIFOI": 47006,
      "DIIDBBGLDOL": "POText_088",
      "OMPENGGFEFF": "POText_109",
      "KEGJJDPAKOH": 2,
      "OEAEJKCIIGP": "POText_102",
      "PLHNMNLGMFE": "POText_159",
      "GOJEHMGFBPK": "POText_159",
      "BGFCAHFBJCO": 1,
      "IIEMNPJFNJD": "Assets/NapResources/UI/Sprite/MainCityNyakichi/Packer/StickerFinish.png",
      "OCNMOCIEKFJ": "POText_112"
    },
    {
      "OLDNPNKKDNE": 47001085,
      "MONKHGDIFOI": 47006,
      "DIIDBBGLDOL": "POText_089",
      "OMPENGGFEFF": "POText_109",
      "KEGJJDPAKOH": 2,
      "OEAEJKCIIGP": "POText_102",
      "PLHNMNLGMFE": "POText_160",
      "GOJEHMGFBPK": "POText_160",
      "BGFCAHFBJCO": 1,
      "IIEMNPJFNJD": "Assets/NapResources/UI/Sprite/MainCityNyakichi/Packer/StickerFinish.png",
      "OCNMOCIEKFJ": "POText_112"
    },
    {
      "OLDNPNKKDNE": 47001086,
      "MONKHGDIFOI": 47006,
      "DIIDBBGLDOL": "POText_090",
      "OMPENGGFEFF": "POText_109",
      "KEGJJDPAKOH": 2,
      "OEAEJKCIIGP": "POText_102",
      "PLHNMNLGMFE": "POText_161",
      "GOJEHMGFBPK": "POText_161",
      "BGFCAHFBJCO": 1,
      "IIEMNPJFNJD": "Assets/NapResources/UI/Sprite/MainCityNyakichi/Packer/StickerFinish.png",
      "OCNMOCIEKFJ": "POText_112"
    },
    {
      "OLDNPNKKDNE": 47001087,
      "MONKHGDIFOI": 47006,
      "DIIDBBGLDOL": "POText_091",
      "OMPENGGFEFF": "POText_109",
      "KEGJJDPAKOH": 1,
      "OEAEJKCIIGP": "",
      "PLHNMNLGMFE": "POText_196",
      "GOJEHMGFBPK": "POText_204",
      "BGFCAHFBJCO": 1,
      "IIEMNPJFNJD": "Assets/NapResources/UI/Sprite/MainCityNyakichi/Packer/StickerFinish.png",
      "OCNMOCIEKFJ": ""
    },
    {
      "OLDNPNKKDNE": 47001088,
      "MONKHGDIFOI": 47006,
      "DIIDBBGLDOL": "POText_092",
      "OMPENGGFEFF": "POText_109",
      "KEGJJDPAKOH": 1,
      "OEAEJKCIIGP": "",
      "PLHNMNLGMFE": "POText_197",
      "GOJEHMGFBPK": "POText_205",
      "BGFCAHFBJCO": 1,
      "IIEMNPJFNJD": "Assets/NapResources/UI/Sprite/MainCityNyakichi/Packer/StickerFinish.png",
      "OCNMOCIEKFJ": ""
    },
    {
      "OLDNPNKKDNE": 47001089,
      "MONKHGDIFOI": 47006,
      "DIIDBBGLDOL": "POText_093",
      "OMPENGGFEFF": "POText_109",
      "KEGJJDPAKOH": 1,
      "OEAEJKCIIGP": "",
      "PLHNMNLGMFE": "POText_198",
      "GOJEHMGFBPK": "POText_206",
      "BGFCAHFBJCO": 1,
      "IIEMNPJFNJD": "Assets/NapResources/UI/Sprite/MainCityNyakichi/Packer/StickerFinish.png",
      "OCNMOCIEKFJ": ""
    },
    {
      "OLDNPNKKDNE": 47001090,
      "MONKHGDIFOI": 47006,
      "DIIDBBGLDOL": "POText_094",
      "OMPENGGFEFF": "POText_109",
      "KEGJJDPAKOH": 1,
      "OEAEJKCIIGP": "",
      "PLHNMNLGMFE": "POText_199",
      "GOJEHMGFBPK": "POText_207",
      "BGFCAHFBJCO": 1,
      "IIEMNPJFNJD": "Assets/NapResources/UI/Sprite/MainCityNyakichi/Packer/StickerFinish.png",
      "OCNMOCIEKFJ": ""
    },
    {
      "OLDNPNKKDNE": 47001091,
      "MONKHGDIFOI": 47006,
      "DIIDBBGLDOL": "POText_095",
      "OMPENGGFEFF": "POText_109",
      "KEGJJDPAKOH": 1,
      "OEAEJKCIIGP": "",
      "PLHNMNLGMFE": "POText_200",
      "GOJEHMGFBPK": "POText_208",
      "BGFCAHFBJCO": 1,
      "IIEMNPJFNJD": "Assets/NapResources/UI/Sprite/MainCityNyakichi/Packer/StickerFinish.png",
      "OCNMOCIEKFJ": ""
    },
    {
      "OLDNPNKKDNE": 47001092,
      "MONKHGDIFOI": 47006,
      "DIIDBBGLDOL": "POText_096",
      "OMPENGGFEFF": "POText_109",
      "KEGJJDPAKOH": 1,
      "OEAEJKCIIGP": "",
      "PLHNMNLGMFE": "POText_201",
      "GOJEHMGFBPK": "POText_209",
      "BGFCAHFBJCO": 1,
      "IIEMNPJFNJD": "Assets/NapResources/UI/Sprite/MainCityNyakichi/Packer/StickerFinish.png",
      "OCNMOCIEKFJ": ""
    },
    {
      "OLDNPNKKDNE": 47001093,
      "MONKHGDIFOI": 47006,
      "DIIDBBGLDOL": "POText_097",
      "OMPENGGFEFF": "POText_109",
      "KEGJJDPAKOH": 1,
      "OEAEJKCIIGP": "",
      "PLHNMNLGMFE": "POText_202",
      "GOJEHMGFBPK": "POText_210",
      "BGFCAHFBJCO": 1,
      "IIEMNPJFNJD": "Assets/NapResources/UI/Sprite/MainCityNyakichi/Packer/StickerFinish.png",
      "OCNMOCIEKFJ": ""
    },
    {
      "OLDNPNKKDNE": 47001094,
      "MONKHGDIFOI": 47006,
      "DIIDBBGLDOL": "POText_098",
      "OMPENGGFEFF": "POText_109",
      "KEGJJDPAKOH": 1,
      "OEAEJKCIIGP": "",
      "PLHNMNLGMFE": "POText_203",
      "GOJEHMGFBPK": "POText_211",
      "BGFCAHFBJCO": 1,
      "IIEMNPJFNJD": "Assets/NapResources/UI/Sprite/MainCityNyakichi/Packer/StickerFinish.png",
      "OCNMOCIEKFJ": ""
    },
    {
      "OLDNPNKKDNE": 47001095,
      "MONKHGDIFOI": 47006,
      "DIIDBBGLDOL": "POText_099",
      "OMPENGGFEFF": "POText_109",
      "KEGJJDPAKOH": 1,
      "OEAEJKCIIGP": "",
      "PLHNMNLGMFE": "POText_123",
      "GOJEHMGFBPK": "POText_123",
      "BGFCAHFBJCO": 1,
      "IIEMNPJFNJD": "Assets/NapResources/UI/Sprite/MainCityNyakichi/Packer/StickerFinish.png",
      "OCNMOCIEKFJ": ""
    },
    {
      "OLDNPNKKDNE": 47001096,
      "MONKHGDIFOI": 47006,
      "DIIDBBGLDOL": "POText_100",
      "OMPENGGFEFF": "POText_109",
      "KEGJJDPAKOH": 1,
      "OEAEJKCIIGP": "",
      "PLHNMNLGMFE": "POText_124",
      "GOJEHMGFBPK": "POText_124",
      "BGFCAHFBJCO": 1,
      "IIEMNPJFNJD": "Assets/NapResources/UI/Sprite/MainCityNyakichi/Packer/StickerFinish.png",
      "OCNMOCIEKFJ": ""
    }
  ]
}