{
  "GMNCBMLIHPE": [
    {
      "DMGGPPNFJKG": 100,
      "NPPIENDILLB": 1,
      "CCFLDEFJLLL": 11103
    },
    {
      "DMGGPPNFJKG": 200,
      "NPPIENDILLB": 2,
      "CCFLDEFJLLL": 12103
    },
    {
      "DMGGPPNFJKG": 300,
      "NPPIENDILLB": 3,
      "CCFLDEFJLLL": 13103
    },
    {
      "DMGGPPNFJKG": 401,
      "NPPIENDILLB": 4,
      "CCFLDEFJLLL": 12102
    },
    {
      "DMGGPPNFJKG": 402,
      "NPPIENDILLB": 4,
      "CCFLDEFJLLL": 11102
    },
    {
      "DMGGPPNFJKG": 403,
      "NPPIENDILLB": 4,
      "CCFLDEFJLLL": 13102
    },
    {
      "DMGGPPNFJKG": 404,
      "NPPIENDILLB": 4,
      "CCFLDEFJLLL": 20103
    },
    {
      "DMGGPPNFJKG": 405,
      "NPPIENDILLB": 4,
      "CCFLDEFJLLL": 21103
    },
    {
      "DMGGPPNFJKG": 406,
      "NPPIENDILLB": 4,
      "CCFLDEFJLLL": 31203
    },
    {
      "DMGGPPNFJKG": 501,
      "NPPIENDILLB": 5,
      "CCFLDEFJLLL": 12102
    },
    {
      "DMGGPPNFJKG": 502,
      "NPPIENDILLB": 5,
      "CCFLDEFJLLL": 11102
    },
    {
      "DMGGPPNFJKG": 503,
      "NPPIENDILLB": 5,
      "CCFLDEFJLLL": 13102
    },
    {
      "DMGGPPNFJKG": 504,
      "NPPIENDILLB": 5,
      "CCFLDEFJLLL": 23103
    },
    {
      "DMGGPPNFJKG": 505,
      "NPPIENDILLB": 5,
      "CCFLDEFJLLL": 31503
    },
    {
      "DMGGPPNFJKG": 506,
      "NPPIENDILLB": 5,
      "CCFLDEFJLLL": 31603
    },
    {
      "DMGGPPNFJKG": 507,
      "NPPIENDILLB": 5,
      "CCFLDEFJLLL": 31703
    },
    {
      "DMGGPPNFJKG": 508,
      "NPPIENDILLB": 5,
      "CCFLDEFJLLL": 31803
    },
    {
      "DMGGPPNFJKG": 509,
      "NPPIENDILLB": 5,
      "CCFLDEFJLLL": 31903
    },
    {
      "DMGGPPNFJKG": 601,
      "NPPIENDILLB": 6,
      "CCFLDEFJLLL": 12102
    },
    {
      "DMGGPPNFJKG": 602,
      "NPPIENDILLB": 6,
      "CCFLDEFJLLL": 11102
    },
    {
      "DMGGPPNFJKG": 603,
      "NPPIENDILLB": 6,
      "CCFLDEFJLLL": 13102
    },
    {
      "DMGGPPNFJKG": 604,
      "NPPIENDILLB": 6,
      "CCFLDEFJLLL": 31402
    },
    {
      "DMGGPPNFJKG": 605,
      "NPPIENDILLB": 6,
      "CCFLDEFJLLL": 12202
    },
    {
      "DMGGPPNFJKG": 606,
      "NPPIENDILLB": 6,
      "CCFLDEFJLLL": 30502
    }
  ]
}